textstats/__init__.py
textstatscomp-0.1.1.dist-info/licenses/LICENSE
textstatscomp-0.1.1.dist-info/METADATA
textstatscomp-0.1.1.dist-info/WHEEL
textstatscomp-0.1.1.dist-info/top_level.txt
textstatscomp-0.1.1.dist-info/RECORD
