Metadata-Version: 2.4
Name: textstatscomp
Version: 0.1.1
Summary: A simple text statistics analyzer for Python
Author-email: Parthiv Godrihal <parthivgod@gmail.com>
License: MIT
Keywords: text,statistics,nlp,analysis,word-count
Classifier: Development Status :: 3 - Alpha
Classifier: Intended Audience :: Developers
Classifier: Topic :: Text Processing :: Linguistic
Classifier: License :: OSI Approved :: MIT License
Classifier: Programming Language :: Python :: 3
Classifier: Programming Language :: Python :: 3.7
Classifier: Programming Language :: Python :: 3.8
Classifier: Programming Language :: Python :: 3.9
Classifier: Programming Language :: Python :: 3.10
Classifier: Programming Language :: Python :: 3.11
Requires-Python: >=3.7
License-File: LICENSE
Dynamic: license-file
